hidevals/__init__.py
hidevals/admin.py
hidevals/api.py
hidevals/db_default.py
hidevals/filter.py
hidevals/templates/admin_hidevals.html
TracHideVals-3.1.dist-info/METADATA
TracHideVals-3.1.dist-info/WHEEL
TracHideVals-3.1.dist-info/entry_points.txt
TracHideVals-3.1.dist-info/top_level.txt
TracHideVals-3.1.dist-info/RECORD
