Metadata-Version: 2.1
Name: TracHideVals
Version: 3.1
Summary: Hide ticket option values from certain users.
Home-page: https://trac-hacks.org/wiki/HideValsPlugin
Author: Noah Kantrowitz, Iker Jimenez
Author-email: noah@coderanger.net, iker.jimenez@gmail.com
License: BSD
Keywords: trac plugin
Platform: UNKNOWN
Classifier: Environment :: Plugins
Classifier: Environment :: Web Environment
Classifier: Framework :: Trac
Classifier: Intended Audience :: System Administrators
Classifier: License :: OSI Approved :: BSD License
Classifier: Natural Language :: English
Classifier: Operating System :: OS Independent
Classifier: Programming Language :: Python :: 2
Classifier: Programming Language :: Python :: 2.7
Classifier: Programming Language :: Python :: 3
Requires-Dist: Trac
